causalnlp/__init__.py
causalnlp/_modidx.py
causalnlp/_nbdev.py
causalnlp/analyzers.py
causalnlp/autocoder.py
causalnlp/key_driver_analysis.py
causalnlp/preprocessing.py
causalnlp/core/__init__.py
causalnlp/core/causalbert.py
causalnlp/core/causalinference.py
causalnlp/meta/__init__.py
causalnlp/meta/base.py
causalnlp/meta/explainer.py
causalnlp/meta/propensity.py
causalnlp/meta/rlearner.py
causalnlp/meta/sensitivity.py
causalnlp/meta/slearner.py
causalnlp/meta/tlearner.py
causalnlp/meta/utils.py
causalnlp/meta/xlearner.py
causalnlp-0.8.1.dist-info/LICENSE
causalnlp-0.8.1.dist-info/METADATA
causalnlp-0.8.1.dist-info/WHEEL
causalnlp-0.8.1.dist-info/entry_points.txt
causalnlp-0.8.1.dist-info/top_level.txt
causalnlp-0.8.1.dist-info/RECORD
