Metadata-Version: 2.1
Name: causalnlp
Version: 0.8.1
Summary: CausalNLP: A Practical Toolkit for Causal Inference with Text
Home-page: https://github.com/amaiya/causalnlp/tree/main/
Author: Arun S. Maiya
Author-email: arun@maiya.net
License: Apache Software License 2.0
Keywords: causality nlp causal-inference natural-language-processing
Classifier: Development Status :: 3 - Alpha
Classifier: Intended Audience :: Developers
Classifier: Natural Language :: English
Classifier: Programming Language :: Python :: 3.9
Classifier: Programming Language :: Python :: 3.10
Classifier: Programming Language :: Python :: 3.11
Classifier: Programming Language :: Python :: 3.12
Classifier: License :: OSI Approved :: Apache Software License
Requires-Python: >=3.9
License-File: LICENSE
Requires-Dist: transformers
Requires-Dist: pandas
Requires-Dist: numpy>=1.18.5
Requires-Dist: scipy>=1.4.1
Requires-Dist: matplotlib
Requires-Dist: pandas>=0.24.1
Requires-Dist: scikit-learn>=0.22.0
Requires-Dist: seaborn
Requires-Dist: Cython>=0.28.0
Requires-Dist: xgboost
Requires-Dist: tqdm
Requires-Dist: lightgbm
Requires-Dist: pygam
Requires-Dist: packaging
Requires-Dist: sentence-transformers
Requires-Dist: shap
Provides-Extra: dev
